funcao/__init__.py
funcao/fc.py
returnofernandofunction-1.0.0.dist-info/licenses/LICENSE.txt
returnofernandofunction-1.0.0.dist-info/METADATA
returnofernandofunction-1.0.0.dist-info/WHEEL
returnofernandofunction-1.0.0.dist-info/top_level.txt
returnofernandofunction-1.0.0.dist-info/RECORD
