Metadata-Version: 2.4
Name: returnofernandofunction
Version: 1.0.0
Summary: Funcao de retorno de dados
Home-page: https://github.com/fernando10092
Author: Fernando de Lima Gomes
Author-email: fernando100@windowslive.com
License: MIT
Project-URL: Código fonte, https://github.com/fernando10092
Project-URL: Download, https://github.com/fernando10092
Keywords: Print Retorno
Classifier: Development Status :: 5 - Production/Stable
Classifier: Intended Audience :: Developers
Classifier: License :: OSI Approved :: MIT License
Classifier: Natural Language :: Portuguese (Brazilian)
Classifier: Operating System :: OS Independent
Classifier: Topic :: Software Development :: Internationalization
Classifier: Topic :: Scientific/Engineering :: Physics
License-File: LICENSE.txt
Dynamic: author
Dynamic: author-email
Dynamic: classifier
Dynamic: description
Dynamic: home-page
Dynamic: keywords
Dynamic: license
Dynamic: license-file
Dynamic: project-url
Dynamic: summary
